idosell/__init__.py
idosell/icdf/__init__.py
idosell/icf/__init__.py
idosell/imf/__init__.py
idosell/iof/__init__.py
idosell/iof/categories.py
idosell/iof/extensions.py
idosell/iof/full.py
idosell/iof/full_change.py
idosell/iof/gateway.py
idosell/iof/light.py
idosell/iof/parameters.py
idosell/iof/preset.py
idosell/iof/producers.py
idosell/iof/series.py
idosell/iof/stocks.py
idosell/iof/units.py
idosell/iof/warranties.py
idosell/isf/__init__.py
python_idosell-0.0.1.dist-info/LICENSE
python_idosell-0.0.1.dist-info/METADATA
python_idosell-0.0.1.dist-info/WHEEL
python_idosell-0.0.1.dist-info/RECORD
